global_meth_package/__init__.py
global_meth_package/branch_and_bound.py
global_meth_package/genetic_algorithm.py
global_meth_package/grid_search.py
global_meth_package/monte_carlo.py
global_meth_package/simulated_annealing.py
global_meth_package/utils.py
global_meth_package-0.1.2.dist-info/METADATA
global_meth_package-0.1.2.dist-info/WHEEL
global_meth_package-0.1.2.dist-info/licenses/LICENSE.txt
global_meth_package-0.1.2.dist-info/RECORD
