Metadata-Version: 2.4
Name: global_meth_package
Version: 0.1.2
Summary: Библиотека, содержащая пять методов глобальной оптимизации: метод ветвей и границ, сеточный поиск, метод Монте-Карло, имитация отжига, генетический алгоритм.
Project-URL: Documetation, https://drive.google.com/drive/folders/10BLl6d3GXtyinTO8jlqDekYjo9K1A3uZ?usp=drive_link
Author-email: Kashina Olesya <kashinaolesya@inbox.ru>
License-Expression: MIT
License-File: LICENSE.txt
Keywords: Monte Carlo,branch and bound,genetic algorithm,global,grid search,optimization,simulated annealing
Classifier: License :: OSI Approved :: MIT License
Classifier: Operating System :: OS Independent
Classifier: Programming Language :: Python :: 3
Requires-Python: >=3.6.0
Requires-Dist: numpy
Provides-Extra: dev
Requires-Dist: pytest; extra == 'dev'
